delinter/__init__.py
delinter/imports.py
delinter/main.py
delinter/unused_imports.py
pydelinter-0.0.3.dist-info/AUTHORS.rst
pydelinter-0.0.3.dist-info/LICENSE.txt
pydelinter-0.0.3.dist-info/METADATA
pydelinter-0.0.3.dist-info/WHEEL
pydelinter-0.0.3.dist-info/entry_points.txt
pydelinter-0.0.3.dist-info/top_level.txt
pydelinter-0.0.3.dist-info/RECORD
