Metadata-Version: 2.1
Name: pydelinter
Version: 0.0.3
Summary: Automatically fix pytlint warnings/errors.
Home-page: https://github.com/gdevanla/pydelinter
Author: grdvnl
Author-email: grdvnl@gmail.com
License: mit
Project-URL: Documentation, https://github.com/gdevanla/pydelinter
Platform: any
Classifier: Development Status :: 4 - Beta
Classifier: Programming Language :: Python
Requires-Dist: libcst (==0.3.14)
Requires-Dist: pylint (==2.4.3)
Provides-Extra: testing
Requires-Dist: pytest ; extra == 'testing'
Requires-Dist: pytest-cov ; extra == 'testing'
